setup.py
Github_url_converter.egg-info/PKG-INFO
Github_url_converter.egg-info/SOURCES.txt
Github_url_converter.egg-info/dependency_links.txt
Github_url_converter.egg-info/entry_points.txt
Github_url_converter.egg-info/top_level.txt
src/__init__.py
src/cli.py
src/helpers.py