Metadata-Version: 1.1
Name: Github-url-converter
Version: 0.1.0
Summary: Quick and easy way to convert Github remote url's from HTTPSto SSH or vice versa
Home-page: https://github.com/aeonaxan/github-url-converter
Author: Ahmed Azaan
Author-email: azaan@outlook.com
License: MIT
Keywords: github convert url
Platform: UNKNOWN
Classifier: Intended Audience :: Developers
Classifier: Natural Language :: English
Classifier: Programming Language :: Python
Classifier: Programming Language :: Python :: 2.7
Classifier: Topic :: Utilities
Classifier: License :: OSI Approved :: MIT License
